{
  "id": "aot-refactor",
  "number": 102,
  "title": "AOT refactor baseline",
  "priority": "high",
  "workstream": "compiler-foundation",
  "domain": "compiler",
  "completedAt": "2026-03-17",
  "milestoneId": "v01-compiler-parity",
  "source": {
    "repo": "compiler",
    "commit": "8079b2e",
    "subject": "AOT Refactor",
    "url": "https://github.com/Cyber-Nomad-Collective/compiler/commit/8079b2e"
  },
  "statusColumn": "Done",
  "body": "Introduces the AOT compilation refactor baseline in the compiler workspace—separating ahead-of-time codegen paths from earlier prototype JIT assumptions.\n\n## Provenance\n- **Repository:** `compiler`\n- **Commit:** [`8079b2e`](https://github.com/Cyber-Nomad-Collective/compiler/commit/8079b2e)\n- **Subject:** AOT Refactor\n- **Completed:** 2026-03-17\n\n## Catalog scope\n- **Delivery version:** v0.1 (Compiler foundation)\n- **Workstream:** `compiler-foundation`\n- **Deliverable:** `v01-compiler-parity`\n\n## Relation\nRequired groundwork for stable `beskid build` / release binaries in v0.1."
}
